{
  "cookies": [
    {
      "name": "YSC",
      "value": "GzIBQP4yjdU",
      "domain": ".youtube.com",
      "path": "/",
      "expires": -1,
      "httpOnly": true,
      "secure": true,
      "sameSite": "None",
      "partitionKey": "https://forstudy.space",
      "_crHasCrossSiteAncestor": true
    },
    {
      "name": "VISITOR_INFO1_LIVE",
      "value": "8N0G_5Ex0SY",
      "domain": ".youtube.com",
      "path": "/",
      "expires": 1773950066.684152,
      "httpOnly": true,
      "secure": true,
      "sameSite": "None",
      "partitionKey": "https://forstudy.space",
      "_crHasCrossSiteAncestor": true
    },
    {
      "name": "VISITOR_PRIVACY_METADATA",
      "value": "CgJVQRIEGgAgSA%3D%3D",
      "domain": ".youtube.com",
      "path": "/",
      "expires": 1773950066.684349,
      "httpOnly": true,
      "secure": true,
      "sameSite": "None",
      "partitionKey": "https://forstudy.space",
      "_crHasCrossSiteAncestor": true
    },
    {
      "name": "__Secure-ROLLOUT_TOKEN",
      "value": "CMvlxajF0NWMhAEQhMCDoY_ojwMYhMCDoY_ojwM%3D",
      "domain": ".youtube.com",
      "path": "/",
      "expires": 1773950066.684566,
      "httpOnly": true,
      "secure": true,
      "sameSite": "None",
      "partitionKey": "https://forstudy.space",
      "_crHasCrossSiteAncestor": true
    },
    {
      "name": "NID",
      "value": "525=KsbHpWo7bMY0ZFPR_eDyB-Wu3z7J9hkK4jhgoAJhP6Cyltdq0bi38MH6KQChboXttgU9NxHuqoWukyyI5v7qw-9a3yizWvoPaKpDaXs4B3_r1z3dsqtHlo5xwalB8KTMoukybBsQKRWOGdibe5Lw0kgoCjJlgDU1RV7t8rqgjB0llJvB8NNQ7yW5yBD3Rz4o",
      "domain": ".google.com",
      "path": "/",
      "expires": 1774209267.59832,
      "httpOnly": true,
      "secure": true,
      "sameSite": "None"
    },
    {
      "name": "sid",
      "value": "s%3AMkx9jruuuigXWzxfFmRMG8Kk7ZBZL8G8.0SIkcfn%2FVV9e7XDtnX9iA%2BQK17EnweaLZeymHimPUwk",
      "domain": ".forstudy.space",
      "path": "/",
      "expires": 1758484468.482085,
      "httpOnly": false,
      "secure": false,
      "sameSite": "Lax"
    }
  ],
  "origins": [
    {
      "origin": "https://www.youtube.com",
      "localStorage": [
        {
          "name": "ytidb::LAST_RESULT_ENTRY_KEY",
          "value": "{\"data\":{\"hasSucceededOnce\":true},\"expiration\":1760990067314,\"creation\":1758398067314}"
        }
      ]
    }
  ]
}